eventsourcing_django/__init__.py
eventsourcing_django/admin.py
eventsourcing_django/apps.py
eventsourcing_django/factory.py
eventsourcing_django/management/commands/sync_followers.py
eventsourcing_django/migrations/0001_initial.py
eventsourcing_django/migrations/__init__.py
eventsourcing_django/models.py
eventsourcing_django/py.typed
eventsourcing_django/recorders.py
eventsourcing_django-0.6.dist-info/LICENSE
eventsourcing_django-0.6.dist-info/METADATA
eventsourcing_django-0.6.dist-info/WHEEL
eventsourcing_django-0.6.dist-info/RECORD
