Metadata-Version: 2.3
Name: eventsourcing-django
Version: 0.6
Summary: Python package for eventsourcing with Django.
License: BSD 3-Clause
Author: John Bywater
Author-email: john.bywater@appropriatesoftware.net
Requires-Python: >=3.9,<4.0
Classifier: Development Status :: 4 - Beta
Classifier: Framework :: Django
Classifier: Framework :: Django :: 4.2
Classifier: Framework :: Django :: 5.0
Classifier: Framework :: Django :: 5.1
Classifier: Framework :: Django :: 5.2
Classifier: License :: OSI Approved :: BSD License
Classifier: License :: Other/Proprietary License
Classifier: Programming Language :: Python
Classifier: Programming Language :: Python :: 3
Classifier: Programming Language :: Python :: 3.9
Classifier: Programming Language :: Python :: 3.10
Classifier: Programming Language :: Python :: 3.11
Classifier: Programming Language :: Python :: 3.12
Classifier: Programming Language :: Python :: 3.13
Requires-Dist: Django (>=4.2,<5.0) ; python_version >= "3.8" and python_version < "3.10"
Requires-Dist: Django (>=4.2,<5.2) ; python_version >= "3.10" and python_version < "3.12"
Requires-Dist: Django (>=5.1,<6.0) ; python_version >= "3.12" and python_version < "4.0"
Requires-Dist: eventsourcing (>=9.3.5,<9.5)
Project-URL: Homepage, https://eventsourcing.readthedocs.io/
Project-URL: Repository, https://github.com/pyeventsourcing/eventsourcing-django
